README.rst
setup.py
spykeutils/__init__.py
spykeutils/_scipy_quantities.py
spykeutils/conversions.py
spykeutils/correlations.py
spykeutils/progress_indicator.py
spykeutils/rate_estimation.py
spykeutils/signal_processing.py
spykeutils/sorting_quality_assesment.py
spykeutils/spike_train_generation.py
spykeutils/spike_train_metrics.py
spykeutils/stationarity.py
spykeutils/tools.py
spykeutils.egg-info/PKG-INFO
spykeutils.egg-info/SOURCES.txt
spykeutils.egg-info/dependency_links.txt
spykeutils.egg-info/entry_points.txt
spykeutils.egg-info/requires.txt
spykeutils.egg-info/top_level.txt
spykeutils/monkeypatch/__init__.py
spykeutils/monkeypatch/quantities_patch.py
spykeutils/plot/__init__.py
spykeutils/plot/analog_signals.py
spykeutils/plot/correlogram.py
spykeutils/plot/dialog.py
spykeutils/plot/guiqwt_tools.py
spykeutils/plot/helper.py
spykeutils/plot/icons_rc.py
spykeutils/plot/interspike_intervals.py
spykeutils/plot/peri_stimulus_histogram.py
spykeutils/plot/rasterplot.py
spykeutils/plot/sde.py
spykeutils/plot/spike_amp_hist.py
spykeutils/plot/spike_waveforms.py
spykeutils/plugin/__init__.py
spykeutils/plugin/analysis_plugin.py
spykeutils/plugin/data_provider.py
spykeutils/plugin/data_provider_neo.py
spykeutils/plugin/data_provider_stored.py
spykeutils/plugin/gui_data.py
spykeutils/plugin/io_plugin.py
spykeutils/plugin/startplugin.py
spykeutils/tests/__init__.py
spykeutils/tests/builders.py
spykeutils/tests/test_quality_assesment.py
spykeutils/tests/test_rate_estimation.py
spykeutils/tests/test_scipy_quantities.py
spykeutils/tests/test_signal_processing.py
spykeutils/tests/test_spike_train_generation.py
spykeutils/tests/test_spike_train_metrics.py
spykeutils/tests/test_tools.py