Metadata-Version: 1.1
Name: spykeutils
Version: 0.4.0
Summary: Utilities for analyzing electrophysiological data
Home-page: https://github.com/rproepp/spykeutils
Author: Robert Pröpper
Author-email: UNKNOWN
License: BSD
Platform: UNKNOWN
Classifier: Development Status :: 4 - Beta
Classifier: Intended Audience :: Science/Research
Classifier: License :: OSI Approved :: BSD License
Classifier: Natural Language :: English
Classifier: Operating System :: OS Independent
Classifier: Programming Language :: Python
Classifier: Topic :: Scientific/Engineering :: Bio-Informatics
